xvideos/__init__.py
xvideos/main.py
xvideos/xvideos.py
xvideos/videos/__init__.py
xvideos/videos/details.py
xvideos/videos/fresh.py
xvideos/videos/search.py
xvideos/videos/verified.py
xvideos/videos/base/__init__.py
xvideos/videos/base/base.py
xvideos/videos/base/details_scraper.py
xvideos/videos/base/parser.py
xvideos/videos/base/video_scraper.py
xvideos/videos/base/config/__init__.py
xvideos/videos/base/config/config.json
xvideos/videos/base/config/config.py
xvideos_py-0.2.0.dist-info/LICENSE
xvideos_py-0.2.0.dist-info/METADATA
xvideos_py-0.2.0.dist-info/WHEEL
xvideos_py-0.2.0.dist-info/entry_points.txt
xvideos_py-0.2.0.dist-info/top_level.txt
xvideos_py-0.2.0.dist-info/RECORD
