Metadata-Version: 2.1
Name: xvideos-py
Version: 0.2.0
Summary: A powerful Python library to scrape xvideos.com
Home-page: https://github.com/OSintt/xvideos.py
Author: OSintt
Author-email: akumagamer123@gmail.com
License: UNKNOWN
Platform: UNKNOWN
Classifier: Programming Language :: Python :: 3
Classifier: License :: OSI Approved :: MIT License
Classifier: Operating System :: OS Independent
Requires-Python: >=3.6
License-File: LICENSE
Requires-Dist: beautifulsoup4
Requires-Dist: requests
Requires-Dist: playwright
